KS.cp313-win_amd64.pyd
ks1beta-0.5.0.dist-info/METADATA
ks1beta-0.5.0.dist-info/WHEEL
ks1beta-0.5.0.dist-info/top_level.txt
ks1beta-0.5.0.dist-info/RECORD
