Metadata-Version: 2.4
Name: KS1Beta
Version: 0.5.0
Summary: A C-extension library that outperforms NumPy via O(1) complexity.
Dynamic: description
Dynamic: description-content-type
Dynamic: summary
